goldendoodle/.gitignore
goldendoodle/.vscode/configurationCache.log
goldendoodle/.vscode/dryrun.log
goldendoodle/.vscode/launch.json
goldendoodle/.vscode/settings.json
goldendoodle/.vscode/targets.log
goldendoodle/apidoc-sphinx.sh
goldendoodle/chrome_extensions/GoFullPageFull-Page-Screen-Capture.crx.tobedeleted
goldendoodle/docs/Makefile
goldendoodle/docs/build/.buildinfo
goldendoodle/docs/build/.doctrees/changelog.doctree
goldendoodle/docs/build/.doctrees/concepts.doctree
goldendoodle/docs/build/.doctrees/environment.pickle
goldendoodle/docs/build/.doctrees/goldendoodle.doctree
goldendoodle/docs/build/.doctrees/goldendoodle.middlewares.doctree
goldendoodle/docs/build/.doctrees/goldendoodle.pipelines.doctree
goldendoodle/docs/build/.doctrees/goldendoodle.settings.doctree
goldendoodle/docs/build/.doctrees/goldendoodle.spider.utils.doctree
goldendoodle/docs/build/.doctrees/goldendoodle.spiders.doctree
goldendoodle/docs/build/.doctrees/goldendoodle.spiders.items.doctree
goldendoodle/docs/build/.doctrees/goldendoodle.spiders.recherchedechaîne_gldnddl.doctree
goldendoodle/docs/build/.doctrees/goldendoodle.spiders.utils.doctree
goldendoodle/docs/build/.doctrees/goldendoodle.spiders.utils.gldnddl_utils.doctree
goldendoodle/docs/build/.doctrees/goldendoodle.spiders.utils.seticecream.doctree
goldendoodle/docs/build/.doctrees/index.doctree
goldendoodle/docs/build/.doctrees/modules.doctree
goldendoodle/docs/build/_images/search_tool_decision.drawio.svg
goldendoodle/docs/build/_modules/goldendoodle/middlewares.html
goldendoodle/docs/build/_modules/goldendoodle/pipelines.html
goldendoodle/docs/build/_modules/goldendoodle/spiders/items.html
goldendoodle/docs/build/_modules/goldendoodle/spiders/recherchedechaîne_gldnddl.html
goldendoodle/docs/build/_modules/goldendoodle/spiders/utils/gldnddl_utils.html
goldendoodle/docs/build/_modules/goldendoodle/spiders/utils/seticecream.html
goldendoodle/docs/build/_modules/index.html
goldendoodle/docs/build/_sources/changelog.rst.txt
goldendoodle-23.dist-info/LICENSE
goldendoodle-23.dist-info/LICENSE.html
goldendoodle-23.dist-info/WHEEL
goldendoodle-23.dist-info/METADATA
goldendoodle-23.dist-info/RECORD
