Metadata-Version: 2.1
Name: goldendoodle
Version: 23
Summary: Scrapy helper
License: MIT
Author: Wilfried Dehnen
Author-email: wilfried.dehnen@gmx.de
Requires-Python: >=3.11,<4.0
Classifier: License :: OSI Approved :: MIT License
Classifier: Programming Language :: Python :: 3
Requires-Dist: beautifulsoup4 (>=4.11.1,<5.0.0)
Requires-Dist: cryptography (<38)
Requires-Dist: lxml (>=4.9.2,<5.0.0)
Requires-Dist: myst-parser (>=0.18.1,<0.19.0)
Requires-Dist: regex (>=2022.10.31,<2023.0.0)
Requires-Dist: scrapy-selenium-middleware (>=0.0.5,<0.0.6)
Requires-Dist: tldextract (>=3.4.0,<4.0.0)
Requires-Dist: webdriver-manager (>=3.8.5,<4.0.0)
